pydcapi/__init__.py
pydcapi/client.py
pydcapi/credentials.py
pydcapi/transports.py
pydcapi/models/asset_block_upload_extend_parameters_v1/__init__.py
pydcapi/models/asset_block_upload_extend_v1/__init__.py
pydcapi/models/asset_block_upload_finalize_parameters_v1/__init__.py
pydcapi/models/asset_block_upload_finalize_v1/__init__.py
pydcapi/models/asset_block_upload_initialize_parameters_v1/__init__.py
pydcapi/models/asset_block_upload_initialize_v1/__init__.py
pydcapi/models/asset_document_rendition_status_v1/__init__.py
pydcapi/models/asset_export_v1/__init__.py
pydcapi/models/asset_import_v1/__init__.py
pydcapi/models/asset_metadata_basic_v1/__init__.py
pydcapi/models/asset_metadata_field_patch_v1/__init__.py
pydcapi/models/asset_metadata_field_v1/__init__.py
pydcapi/models/asset_tag_sensei_contentanalyzer_v1/__init__.py
pydcapi/models/asset_tag_sensei_v1/__init__.py
pydcapi/models/asset_upload_parameters_v1/__init__.py
pydcapi/models/asset_uri_download_v1/__init__.py
pydcapi/models/asset_uri_rendition_v1/__init__.py
pydcapi/models/asset_v1/__init__.py
pydcapi/models/authorize_client_verb_v1/__init__.py
pydcapi/models/compute_content_bboxes_parameters_v1/__init__.py
pydcapi/models/connector_delete_response_v1/__init__.py
pydcapi/models/connector_info_v1/__init__.py
pydcapi/models/connector_link_parameters_v1/__init__.py
pydcapi/models/connector_listing_v1/__init__.py
pydcapi/models/copy_op_params_v1/__init__.py
pydcapi/models/copy_to_user_parameters_v1/__init__.py
pydcapi/models/create_record/__init__.py
pydcapi/models/createpdf_from_html_parameters_v1/__init__.py
pydcapi/models/createpdf_options_v1/__init__.py
pydcapi/models/createpdf_parameters_v1/__init__.py
pydcapi/models/discovery_v1/__init__.py
pydcapi/models/exportpdf_options_v1/__init__.py
pydcapi/models/exportpdf_parameters_v1/__init__.py
pydcapi/models/feedback_creation_v1/__init__.py
pydcapi/models/folder_breadcrumbs_v1/__init__.py
pydcapi/models/folder_creation_v1/__init__.py
pydcapi-0.1.7.dist-info/METADATA
pydcapi-0.1.7.dist-info/WHEEL
pydcapi-0.1.7.dist-info/licenses/LICENSE
pydcapi-0.1.7.dist-info/RECORD
