Metadata-Version: 2.3
Name: pydcapi
Version: 0.1.7
Summary: Unofficial Python library for Adobe Document Cloud
Project-URL: GitHub, https://github.com/mkuznets/pydcapi
Author-email: Max Kuznetsov <maks.kuznetsov@gmail.com>
License-File: LICENSE
Requires-Python: >=3.8
Requires-Dist: httpx>=0.20.0
Requires-Dist: pydantic>=2.0
Requires-Dist: uritemplate>=3.0.1
